setup.py
CmdUtils.egg-info/PKG-INFO
CmdUtils.egg-info/SOURCES.txt
CmdUtils.egg-info/dependency_links.txt
CmdUtils.egg-info/entry_points.txt
CmdUtils.egg-info/not-zip-safe
CmdUtils.egg-info/top_level.txt
cmdutils/__init__.py
cmdutils/arg.py
cmdutils/log.py
cmdutils/templates.py