Metadata-Version: 1.0
Name: CmdUtils
Version: 0.1
Summary: Routines to help make command-line utilities easier to write
Home-page: http://pythonpaste.org/cmdutils/
Author: Ian Bicking
Author-email: ianb@colorstudy.com
License: MIT
Keywords: command line option parsing optparse
Platform: UNKNOWN
Classifier: Development Status :: 4 - Beta
Classifier: Intended Audience :: Developers
Classifier: License :: OSI Approved :: MIT License
Classifier: Environment :: Console
